README.rst
setup.cfg
setup.py
surfify/__init__.py
surfify/info.py
surfify.egg-info/PKG-INFO
surfify.egg-info/SOURCES.txt
surfify.egg-info/dependency_links.txt
surfify.egg-info/requires.txt
surfify.egg-info/top_level.txt
surfify/augmentation/__init__.py
surfify/augmentation/base.py
surfify/augmentation/mixup.py
surfify/augmentation/utils.py
surfify/datasets/__init__.py
surfify/datasets/_samples_generator.py
surfify/losses/__init__.py
surfify/losses/vae.py
surfify/models/__init__.py
surfify/models/base.py
surfify/models/unet.py
surfify/models/vae.py
surfify/models/vgg.py
surfify/nn/__init__.py
surfify/nn/functional.py
surfify/nn/modules.py
surfify/plotting/__init__.py
surfify/plotting/surface.py
surfify/resources/freesurfer_icos.npz
surfify/tests/test_augmentation.py
surfify/tests/test_datasets.py
surfify/tests/test_models_unet.py
surfify/tests/test_models_vae.py
surfify/tests/test_models_vgg.py
surfify/tests/test_nn_modules.py
surfify/tests/test_plotting_surface.py
surfify/tests/test_utils_coord.py
surfify/tests/test_utils_io.py
surfify/tests/test_utils_logging.py
surfify/tests/test_utils_sampling.py
surfify/utils/__init__.py
surfify/utils/coord.py
surfify/utils/io.py
surfify/utils/sampling.py