Metadata-Version: 1.1
Name: surfify
Version: 0.2.0
Summary: 
